LICENSE
incolumepy/gwa/__init__.py
incolumepy/gwa/hello.py
incolumepy/gwa/version.txt
pyproject.toml
incolumepy.gwa-0.6.2.dist-info/LICENSE
incolumepy.gwa-0.6.2.dist-info/WHEEL
incolumepy.gwa-0.6.2.dist-info/METADATA
incolumepy.gwa-0.6.2.dist-info/RECORD
