Metadata-Version: 2.1
Name: incolumepy.gwa
Version: 0.6.2
Summary: Prospections from Github Workflows Actions
License: BSD 2-Clause License
Author: Britodfbr
Author-email: britodfbr@gmail.com
Requires-Python: >=3.6.8,<4
Classifier: License :: Other/Proprietary License
Classifier: Programming Language :: Python :: 3
Classifier: Programming Language :: Python :: 3.10
Classifier: Programming Language :: Python :: 3.7
Classifier: Programming Language :: Python :: 3.8
Classifier: Programming Language :: Python :: 3.9
Requires-Dist: toml[tomli] (>=0.10.2,<0.11.0)
Project-URL: Bug Tracker, https://github.com/incolumepy-prospections/incolumepy.gwa/issues
Project-URL: homepage, https://pypi.org/project/incolumepy.gwa
Project-URL: license, https://github.com/incolumepy-prospections/incolumepy.gwa/blob/main/LICENSE
Project-URL: repository, https://github.com/incolumepy-prospections/incolumepy.gwa
